jellyfinapi/__init__.py
jellyfinapi/api_helper.py
jellyfinapi/configuration.py
jellyfinapi/decorators.py
jellyfinapi/jellyfinapi_client.py
jellyfinapi/controllers/__init__.py
jellyfinapi/controllers/activity_log_controller.py
jellyfinapi/controllers/api_key_controller.py
jellyfinapi/controllers/artists_controller.py
jellyfinapi/controllers/audio_controller.py
jellyfinapi/controllers/base_controller.py
jellyfinapi/controllers/branding_controller.py
jellyfinapi/controllers/channels_controller.py
jellyfinapi/controllers/client_log_controller.py
jellyfinapi/controllers/collection_controller.py
jellyfinapi/controllers/configuration_controller.py
jellyfinapi/controllers/dashboard_controller.py
jellyfinapi/controllers/devices_controller.py
jellyfinapi/controllers/display_preferences_controller.py
jellyfinapi/controllers/dlna_controller.py
jellyfinapi/controllers/dlna_server_controller.py
jellyfinapi/controllers/dynamic_hls_controller.py
jellyfinapi/controllers/endpoints_controller.py
jellyfinapi/controllers/environment_controller.py
jellyfinapi/controllers/filter_controller.py
jellyfinapi/controllers/genres_controller.py
jellyfinapi/controllers/hls_segment_controller.py
jellyfinapi/controllers/image_by_name_controller.py
jellyfinapi/controllers/image_controller.py
jellyfinapi/controllers/instant_mix_controller.py
jellyfinapi/controllers/item_lookup_controller.py
jellyfinapi/controllers/item_refresh_controller.py
jellyfinapi/controllers/item_update_controller.py
jellyfinapi/controllers/items_controller.py
jellyfinapi/controllers/library_controller.py
jellyfinapi/controllers/library_structure_controller.py
jellyfinapi/controllers/live_tv_controller.py
jellyfinapi/controllers/localization_controller.py
jellyfinapi/controllers/media_info_controller.py
jellyfinapi/controllers/movies_controller.py
jellyfinapi/controllers/music_genres_controller.py
jellyfinapi/controllers/notifications_controller.py
jellyfinapi/controllers/open_subtitles_controller.py
jellyfinapi-10.8.5.dist-info/METADATA
jellyfinapi-10.8.5.dist-info/WHEEL
jellyfinapi-10.8.5.dist-info/top_level.txt
jellyfinapi-10.8.5.dist-info/RECORD
