Metadata-Version: 2.1
Name: jellyfinapi
Version: 10.8.5
Summary: Python client library for Jellyfin API
Home-page: https://github.com/radityaharya/jellyfinapi
Author: Raditya Harya
Author-email: radityaharya02@gmail.com
Requires-Dist: jsonpickle (>=1.4.1,~=1.4)
Requires-Dist: requests (~=2.25)
Requires-Dist: cachecontrol (~=0.12.6)
Requires-Dist: python-dateutil (~=2.8.1)
Requires-Dist: enum34 (>=1.1.10,~=1.1)
Requires-Dist: deprecation (~=2.1)
